make_query_param_filters/__init__.py
make_query_param_filters/__main__.py
make_query_params_filters-0.0.1.dist-info/LICENSE
make_query_params_filters-0.0.1.dist-info/METADATA
make_query_params_filters-0.0.1.dist-info/WHEEL
make_query_params_filters-0.0.1.dist-info/top_level.txt
make_query_params_filters-0.0.1.dist-info/RECORD
