Metadata-Version: 2.1
Name: make-query-params-filters
Version: 0.0.1
Author-email: Lucas Gasque <lucasfdg@hotmail.com>
Project-URL: Homepage, https://github.com/LucasGasque/make-query-params-filters
Project-URL: Issues, https://github.com/LucasGasque/make-query-params-filters/issues
Requires-Python: >=3.9
License-File: LICENSE
Requires-Dist: sqlalchemy
Provides-Extra: test
Requires-Dist: pytest ; extra == 'test'
Requires-Dist: pytest-cov ; extra == 'test'
Requires-Dist: flake8 ; extra == 'test'
